<?xml version="1.0" encoding="utf-8"?>
<!DOCTYPE hibernate-mapping PUBLIC "-//Hibernate/Hibernate Mapping DTD 3.0//EN"
"http://hibernate.sourceforge.net/hibernate-mapping-3.0.dtd">
<!-- 
    Mapping file autogenerated by MyEclipse Persistence Tools
-->
<hibernate-mapping>
    <class name="org.eapp.oa.device.hbean.PurchaseDevice" table="OA_PurchaseDevice">
        <comment>设备</comment>
        <id name="id" type="java.lang.String">
            <column name="ID_" length="36" />
            <generator class="uuid.hex"></generator>
        </id>
        <many-to-one name="deviceClass" class="org.eapp.oa.device.hbean.DeviceClass" fetch="select" lazy="false">
            <column name="DEVICECLASS_" length="36" />
        </many-to-one>
        <many-to-one name="devPurchaseForm" class="org.eapp.oa.device.hbean.DevPurchaseForm" fetch="select" lazy="false">
            <column name="PURCHASEFORMID_" length="36">
                <comment>设备领用、申购、调拨单ID</comment>
            </column>
        </many-to-one>
        <property name="deviceName" type="java.lang.String">
            <column name="DEVICENAME_" length="128">
                <comment>设备名称 DeviceName_</comment>
            </column>
        </property>
        <property name="deviceModel" type="java.lang.String">
            <column name="DEVICEMODEL_" length="128">
                <comment>设备型号 DeviceModel_</comment>
            </column>
        </property>
        <property name="description" type="java.lang.String">
            <column name="DESCRIPTION_" length="2000">
                <comment>设备描述 Description_</comment>
            </column>
        </property>
        <property name="buyTime" type="java.util.Date">
            <column name="BUYTIME_">
                <comment>购买时间 BuyTime_</comment>
            </column>
        </property>
        <property name="deductFlag" type="java.lang.Boolean">
            <column name="DEDUCTFLAG_" >
                <comment>是否扣款 IsMoney_ 0：不扣 1：扣款</comment>
            </column>
        </property>
        <property name="deductMoney" type="java.lang.Double">
            <column name="DEDUCTMONEY_" precision="16">
                <comment>扣款金额 DeductMoney_</comment>
            </column>
        </property>
        <property name="inDate" type="java.util.Date">
            <column name="INDATE_">
                <comment>到账日期 InDate_</comment>
            </column>
        </property>
        <property name="price" type="java.lang.Double">
            <column name="PRICE_" precision="16" />
        </property>
       <property name="deviceCfgDesc" type="java.lang.String">
            <column name="DEVICECFGDESC_" length="2000" />
        </property>
		<property name="belongtoAreaCode" type="java.lang.String">
            <column name="BELONGTOAREACODE_" length="128" />
        </property>
        <property name="areaCode" type="java.lang.String">
            <column name="AREACODE_" length="128" />
        </property>
        <property name="purpose" type="java.lang.String">
            <column name="PURPOSE_" />
        </property>
        <property name="planUseDate" type="java.util.Date">
            <column name="PLANUSEDATE_" />
        </property>
        <property name="deviceID" type="java.lang.String">
            <column name="DEVICEID_" length="36" />
        </property>
        <property name="returnBackDate" type="java.util.Date">
            <column name="RETURNBACKDATE_" />
        </property>
        <property name="displayOrder" type="java.lang.Integer">
            <column name="DISPLAYORDER_"/>
        </property>		
		<one-to-one name="devValidateForm" class="org.eapp.oa.device.hbean.DevValidateForm" lazy="false" property-ref="purchaseDevice" cascade="all"></one-to-one>
        <set name="devicePropertyDetails" inverse="true" cascade="all,delete-orphan" order-by="PROPERTYNAME_" lazy="false">
            <key>
                <column name="PURCHASEDEVID_" length="36">
                    <comment>申购设备ID PURCHASEDEVICEID_</comment>
                </column>
            </key>
            <one-to-many class="org.eapp.oa.device.hbean.DevicePropertyDetail" />
        </set>
    </class>
</hibernate-mapping>
