<?xml version="1.0" encoding="utf-8"?>
<!DOCTYPE hibernate-mapping PUBLIC "-//Hibernate/Hibernate Mapping DTD 3.0//EN"
"http://hibernate.sourceforge.net/hibernate-mapping-3.0.dtd">
<!-- 
    Mapping file autogenerated by MyEclipse Persistence Tools
-->
<hibernate-mapping>
    <class name="org.eapp.poss.hbean.ContractRegDetail" table="POSS_CONTRACT_REG_DETAIL">
        <id name="id" type="java.lang.String">
            <column name="ID_" length="36" />
            <generator class="uuid.hex" />
        </id>
        <property name="contractNums" type="java.lang.Integer">
            <column name="CONTRACT_NUMS_"/>
        </property>
        <property name="regUser" type="java.lang.String">
            <column name="REG_USER_"/>
        </property>
        <property name="regDate" type="java.util.Date">
            <column name="REG_DATE_"/>
        </property>
        
        <many-to-one name="blankContract" class="org.eapp.poss.hbean.BlankContract">
            <column name="CONTRACT_ID_" length="36" />
        </many-to-one>
    </class>
</hibernate-mapping>
