<?xml version="1.0" encoding="utf-8"?>
<!DOCTYPE hibernate-mapping PUBLIC "-//Hibernate/Hibernate Mapping DTD 3.0//EN"
"http://www.hibernate.org/dtd/hibernate-mapping-3.0.dtd">
<!-- 
    Mapping file autogenerated by MyEclipse Persistence Tools
-->
<hibernate-mapping>
    <class name="org.eapp.hbean.FlowVar" table="EAPP_FLOW_VAR">
        <cache usage="read-write"/>
        <id name="varId" type="java.lang.String">
            <column name="VAR_ID_" length="36" />
            <generator class="uuid2" />
        </id>
        <property name="flowClass" type="java.lang.String">
            <column name="FLOW_CLASS_" length="100" />
        </property>
        <property name="name" type="java.lang.String">
            <column name="NAME_" length="100" />
        </property>
        <property name="displayName" type="java.lang.String">
            <column name="DISPLAY_NAME_" length="200" />
        </property>
        <property name="type" type="java.lang.String">
            <column name="TYPE_" length="20" />
        </property>
        <property name="notNull" type="java.lang.Boolean">
            <column name="NOT_NUL_" />
        </property>
        <property name="globalFlag" type="java.lang.Boolean">
            <column name="GLOBAL_FLAG_" />
        </property>
    </class>
</hibernate-mapping>
