<?xml version="1.0" encoding="utf-8"?>
<!DOCTYPE hibernate-mapping PUBLIC "-//Hibernate/Hibernate Mapping DTD 3.0//EN"
"http://www.hibernate.org/dtd/hibernate-mapping-3.0.dtd">
<!-- 
    Mapping file autogenerated by MyEclipse Persistence Tools
-->
<hibernate-mapping>
    <class name="org.eapp.hbean.Module" table="EAPP_MODULE">
    	<cache usage="read-write"/>
        <id name="moduleID" type="java.lang.String">
            <column name="MODULE_ID_" length="36" />
            <generator class="uuid2"></generator>
        </id>
        <many-to-one name="parentModule" class="org.eapp.hbean.Module" lazy="false" fetch="select">
            <column name="PARENT_MODULE_ID_" length="36" />
        </many-to-one>
        <many-to-one name="subSystem" class="org.eapp.hbean.SubSystem" lazy="false" fetch="select">
            <column name="SUB_SYSTEM_ID_" length="36" not-null="true" />
        </many-to-one>
        <property name="moduleKey" type="java.lang.String">
            <column name="MODULE_KEY_" length="36" />
        </property>
        <property name="name" type="java.lang.String">
            <column name="NAME_" length="100" not-null="true" />
        </property>
        <property name="displayOrder" type="java.lang.Integer">
            <column name="DISPLAY_ORDER_" precision="22" scale="0" />
        </property>
        <property name="url" type="java.lang.String">
            <column name="URL_" length="1024" />
        </property>
        <property name="treeLevel" type="java.lang.Integer">
            <column name="TREE_LEVEL_" precision="22" scale="0" not-null="true" />
        </property>
        <property name="description" type="java.lang.String">
            <column name="DESCRIPTION_" length="1024" />
        </property>
        <set name="childModules" inverse="true" order-by="DISPLAY_ORDER_ asc" lazy="false" batch-size="100">
            <key>
                <column name="PARENT_MODULE_ID_" length="36" />
            </key>
            <one-to-many class="org.eapp.hbean.Module" />
        </set>
        <set name="moduleActions" inverse="true">
            <key>
                <column name="MODULE_ID_" length="36" not-null="true" />
            </key>
            <one-to-many class="org.eapp.hbean.ModuleAction" />
        </set>
        <many-to-one name="quoteModule" class="org.eapp.hbean.Module" lazy="false" fetch="select">
            <column name="QUOTE_MODULE_ID_" length="36" />
        </many-to-one>
        <set name="quotedModules" batch-size="10">
            <key>
                <column name="QUOTE_MODULE_ID_" length="36" />
            </key>
            <one-to-many class="org.eapp.hbean.Module" />
        </set>
    </class>
</hibernate-mapping>
